{"platform":"SmartGateway","name":"SmartGateWay","devices":[{"name":"Wifi Smart Plug 2","id":"05200415dc4f22c86dd7","key":"57457a75df5f25c4","ip":"192.168.1.41","type":"tuya","state":true},{"name":"Wifi Smart Plug 3","id":"05200415dc4f22c8708c","key":"3e37547a165c399a","ip":"192.168.1.42","type":"tuya","state":true},{"name":"Master Fan","id":"4486403","key":"4486403","ip":"na","type":"dev433","state":true},{"name":"Cabinet Top","id":"5526835","key":"5526835","ip":"na","type":"dev433","state":false}]}